expkg/__init__.py
expkg/functions.py
expkg_am-0.0.3.dist-info/LICENSE
expkg_am-0.0.3.dist-info/METADATA
expkg_am-0.0.3.dist-info/WHEEL
expkg_am-0.0.3.dist-info/top_level.txt
expkg_am-0.0.3.dist-info/RECORD
